Metadata-Version: 1.0
Name: simp-distributions
Version: 0.1
Summary: Gaussian and Binomial distributions
Home-page: UNKNOWN
Author: Timilehin Aderinola
Author-email: timiderinola@gmail.com
License: UNKNOWN
Platform: UNKNOWN
